webmin_xmlrpc/__init__.py
webmin_xmlrpc/client.py
webmin_xmlrpc/xmlrpc.py
webmin_xmlrpc-0.0.1.dist-info/LICENSE
webmin_xmlrpc-0.0.1.dist-info/METADATA
webmin_xmlrpc-0.0.1.dist-info/WHEEL
webmin_xmlrpc-0.0.1.dist-info/top_level.txt
webmin_xmlrpc-0.0.1.dist-info/RECORD
