Metadata-Version: 2.1
Name: webmin-xmlrpc
Version: 0.0.1
Summary: Provides a python interface to interact with the Webmin XML-RPC API.
Author-email: Sidney Kuyateh <autinerd@kuyateh.eu>
Project-URL: Homepage, https://github.com/autinerd/webmin-xmlrpc
Keywords: webmin,xmlrpc
Classifier: Development Status :: 2 - Pre-Alpha
Classifier: Intended Audience :: Developers
Classifier: License :: OSI Approved :: MIT License
Classifier: Natural Language :: English
Classifier: Programming Language :: Python :: 3 :: Only
License-File: LICENSE
Requires-Dist: aiohttp
